corpstats/__init__.py
corpstats/admin.py
corpstats/apps.py
corpstats/auth_hooks.py
corpstats/managers.py
corpstats/models.py
corpstats/provider.py
corpstats/tasks.py
corpstats/tests.py
corpstats/urls.py
corpstats/views.py
corpstats/migrations/0001_initial.py
corpstats/migrations/0002_auto_20200720_0745.py
corpstats/migrations/__init__.py
corpstats/templates/corpstat/alliancestats.html
corpstats/templates/corpstat/base.html
corpstats/templates/corpstat/corpstats.html
corpstats/templates/corpstat/menu-search-corporation.html
corpstats/templates/corpstat/navigation.html
corpstats/templates/corpstat/search.html
corpstats/templatetags/corp_tags.py
corpstatsii-1.1.9.dist-info/METADATA
corpstatsii-1.1.9.dist-info/WHEEL
corpstatsii-1.1.9.dist-info/licenses/LICENCE
corpstatsii-1.1.9.dist-info/RECORD
