Metadata-Version: 2.4
Name: corpstatsII
Version: 1.1.9
Summary: Extended Corpstats module for AllianceAuth
Project-URL: homepage, https://github.com/DejarW/allianceauth-corpstats-two
Author-email: Jan Winter <jan@mcwinter.org>
License-Expression: GPL-2.0
License-File: LICENCE
Keywords: allianceauth,corpstats
Classifier: Environment :: Web Environment
Classifier: Framework :: Django
Classifier: Framework :: Django :: 4.2
Classifier: Intended Audience :: Developers
Classifier: Operating System :: OS Independent
Classifier: Programming Language :: Python
Classifier: Programming Language :: Python :: 3 :: Only
Classifier: Programming Language :: Python :: 3.10
Classifier: Programming Language :: Python :: 3.11
Classifier: Programming Language :: Python :: 3.12
Classifier: Topic :: Internet :: WWW/HTTP
Classifier: Topic :: Internet :: WWW/HTTP :: Dynamic Content
Requires-Python: >=3.10
Requires-Dist: allianceauth>=4
Requires-Dist: django-esi>=7.0.1
